<?xml version="1.0" encoding="UTF-8"?>
<GenRun Id="impl_1" LaunchPart="xc7a35tcpg236-1" LaunchTime="1527919922">
  <File Type="WBT-USG" Name="usage_statistics_webtalk.html"/>
  <File Type="BG-DRC" Name="COM_11408.drc"/>
  <File Type="BG-BGN" Name="COM_11408.bgn"/>
  <File Type="BITSTR-SYSDEF" Name="COM_11408.sysdef"/>
  <File Type="BITSTR-LTX" Name="debug_nets.ltx"/>
  <File Type="BITSTR-LTX" Name="COM_11408.ltx"/>
  <File Type="BITSTR-MMI" Name="COM_11408.mmi"/>
  <File Type="BITSTR-BMM" Name="COM_11408_bd.bmm"/>
  <File Type="BITSTR-NKY" Name="COM_11408.nky"/>
  <File Type="BITSTR-RBT" Name="COM_11408.rbt"/>
  <File Type="BITSTR-MSK" Name="COM_11408.msk"/>
  <File Type="BG-BIN" Name="COM_11408.bin"/>
  <File Type="BG-BIT" Name="COM_11408.bit"/>
  <File Type="POSTROUTE-PHYSOPT-TIMING-RPX" Name="COM_11408_timing_summary_postroute_physopted.rpx"/>
  <File Type="POSTROUTE-PHYSOPT-TIMING-PB" Name="COM_11408_timing_summary_postroute_physopted.pb"/>
  <File Type="POSTROUTE-PHYSOPT-TIMING" Name="COM_11408_timing_summary_postroute_physopted.rpt"/>
  <File Type="POSTROUTE-PHYSOPT-BLACKBOX-DCP" Name="COM_11408_postroute_physopt_bb.dcp"/>
  <File Type="POSTROUTE-PHYSOPT-DCP" Name="COM_11408_postroute_physopt.dcp"/>
  <File Type="ROUTE-CLK" Name="COM_11408_clock_utilization_routed.rpt"/>
  <File Type="ROUTE-SIMILARITY" Name="COM_11408_incremental_reuse_routed.rpt"/>
  <File Type="ROUTE-TIMING-RPX" Name="COM_11408_timing_summary_routed.rpx"/>
  <File Type="ROUTE-TIMING-PB" Name="COM_11408_timing_summary_routed.pb"/>
  <File Type="ROUTE-TIMINGSUMMARY" Name="COM_11408_timing_summary_routed.rpt"/>
  <File Type="ROUTE-STATUS-PB" Name="COM_11408_route_status.pb"/>
  <File Type="ROUTE-STATUS" Name="COM_11408_route_status.rpt"/>
  <File Type="ROUTE-PWR-RPX" Name="COM_11408_power_routed.rpx"/>
  <File Type="INIT-TIMING" Name="COM_11408_timing_summary_init.rpt"/>
  <File Type="OPT-DRC" Name="COM_11408_drc_opted.rpt"/>
  <File Type="OPT-DCP" Name="COM_11408_opt.dcp"/>
  <File Type="OPT-METHODOLOGY-DRC" Name="COM_11408_methodology_drc_opted.rpt"/>
  <File Type="PLACE-PRE-SIMILARITY" Name="COM_11408_incremental_reuse_pre_placed.rpt"/>
  <File Type="OPT-HWDEF" Name="COM_11408.hwdef"/>
  <File Type="OPT-TIMING" Name="COM_11408_timing_summary_opted.rpt"/>
  <File Type="REPORTS-TCL" Name="COM_11408_reports.tcl"/>
  <File Type="PWROPT-DCP" Name="COM_11408_pwropt.dcp"/>
  <File Type="PWROPT-DRC" Name="COM_11408_drc_pwropted.rpt"/>
  <File Type="RDI-RDI" Name="COM_11408.vdi"/>
  <File Type="PWROPT-TIMING" Name="COM_11408_timing_summary_pwropted.rpt"/>
  <File Type="PLACE-IO" Name="COM_11408_io_placed.rpt"/>
  <File Type="PA-TCL" Name="COM_11408.tcl"/>
  <File Type="PLACE-DCP" Name="COM_11408_placed.dcp"/>
  <File Type="PLACE-CLK" Name="COM_11408_clock_utilization_placed.rpt"/>
  <File Type="PLACE-TIMING" Name="COM_11408_timing_summary_placed.rpt"/>
  <File Type="PLACE-UTIL" Name="COM_11408_utilization_placed.rpt"/>
  <File Type="POSTPLACE-PWROPT-TIMING" Name="COM_11408_timing_summary_postplace_pwropted.rpt"/>
  <File Type="PLACE-UTIL-PB" Name="COM_11408_utilization_placed.pb"/>
  <File Type="PHYSOPT-TIMING" Name="COM_11408_timing_summary_physopted.rpt"/>
  <File Type="PLACE-CTRL" Name="COM_11408_control_sets_placed.rpt"/>
  <File Type="PLACE-SIMILARITY" Name="COM_11408_incremental_reuse_placed.rpt"/>
  <File Type="POSTPLACE-PWROPT-DCP" Name="COM_11408_postplace_pwropt.dcp"/>
  <File Type="PHYSOPT-DCP" Name="COM_11408_physopt.dcp"/>
  <File Type="PHYSOPT-DRC" Name="COM_11408_drc_physopted.rpt"/>
  <File Type="ROUTE-ERROR-DCP" Name="COM_11408_routed_error.dcp"/>
  <File Type="ROUTE-DCP" Name="COM_11408_routed.dcp"/>
  <File Type="ROUTE-BLACKBOX-DCP" Name="COM_11408_routed_bb.dcp"/>
  <File Type="ROUTE-DRC" Name="COM_11408_drc_routed.rpt"/>
  <File Type="ROUTE-METHODOLOGY-DRC" Name="COM_11408_methodology_drc_routed.rpt"/>
  <File Type="ROUTE-DRC-PB" Name="COM_11408_drc_routed.pb"/>
  <File Type="ROUTE-METHODOLOGY-DRC-PB" Name="COM_11408_methodology_drc_routed.pb"/>
  <File Type="ROUTE-DRC-RPX" Name="COM_11408_drc_routed.rpx"/>
  <File Type="ROUTE-PWR" Name="COM_11408_power_routed.rpt"/>
  <File Type="ROUTE-METHODOLOGY-DRC-RPX" Name="COM_11408_methodology_drc_routed.rpx"/>
  <File Type="ROUTE-PWR-SUM" Name="COM_11408_power_summary_routed.pb"/>
  <FileSet Name="sources" Type="DesignSrcs" RelSrcDir="$PSRCDIR/sources_1">
    <Filter Type="Srcs"/>
    <File Path="$PPRDIR/4_7seg.v">
      <FileInfo>
        <Attr Name="UsedIn" Val="synthesis"/>
        <Attr Name="UsedIn" Val="implementation"/>
        <Attr Name="UsedIn" Val="simulation"/>
      </FileInfo>
    </File>
    <Config>
      <Option Name="DesignMode" Val="RTL"/>
      <Option Name="TopModule" Val="COM_11408"/>
      <Option Name="TopAutoSet" Val="TRUE"/>
    </Config>
  </FileSet>
  <FileSet Name="constrs_in" Type="Constrs" RelSrcDir="$PSRCDIR/constrs_1">
    <Filter Type="Constrs"/>
    <File Path="$PPRDIR/4_7seg.xdc">
      <FileInfo>
        <Attr Name="UsedIn" Val="synthesis"/>
        <Attr Name="UsedIn" Val="implementation"/>
      </FileInfo>
    </File>
    <Config>
      <Option Name="ConstrsType" Val="XDC"/>
    </Config>
  </FileSet>
  <Strategy Version="1" Minor="2">
    <StratHandle Name="Vivado Implementation Defaults" Flow="Vivado Implementation 2018"/>
    <Step Id="init_design"/>
    <Step Id="opt_design"/>
    <Step Id="power_opt_design"/>
    <Step Id="place_design"/>
    <Step Id="post_place_power_opt_design"/>
    <Step Id="phys_opt_design"/>
    <Step Id="route_design"/>
    <Step Id="post_route_phys_opt_design"/>
    <Step Id="write_bitstream"/>
  </Strategy>
</GenRun>
